{"name":"hokan","tagline":"Dojo Store API Compliant Persistent Local Storage ","body":"# hokan\r\n\r\n**hokan** is a package of AMD modules that provide tools to work with persistent local storage.  In particular it provides a [Dojo Store API][store-api] interface to persistent local storage.\r\n\r\n## Requirements\r\n\r\nThe modules provided here should work with [Dojo Core][core] 1.8 or later.\r\n\r\n## License\r\n\r\nThis code is licensed under the [\"New\" BSD License](LICENSE).\r\n\r\n## Installation\r\n\r\n**hokan** can be installed via [cpm][cpm], [volo][volo] or [npm][npm], or simply [downloaded][download].\r\n\r\nVia cpm:\r\n\r\n```bash\r\n$ cpm install hokan\r\n```\r\n\r\nVia volo:\r\n\r\n```bash\r\n$ volo add kitsonk/hokan\r\n```\r\n\r\nVia npm:\r\n\r\n```bash\r\n$ npm install hokan\r\n```\r\n\r\n## Modules\r\n\r\nPlease refer to the documentation for each of the modules for specifics of their usage:\r\n\r\n* [LocalStorage](docs/LocalStorage.md) - A Dojo Store API interface to DOM Storage's localStorage\r\n* [IndexedDB](docs/IndexedDB.md) - A Dojo Store API interface to IndexedDB\r\n* [idbQueryEngine](docs/idbQueryEngine.md) - A Dojo Store API query engine that supports querying IndexedDB cursors\r\n* [util](docs/util.md) - Utility functions for *hokan*\r\n\r\n## Testing\r\n\r\nUnit tests require the [D.O.H.][doh] installed and are located in the `tests` path.\r\n\r\n[core]: http://dojotoolkit.org/reference-guide/dojo/\r\n[store-api]: http://dojotoolkit.org/reference-guide/dojo/store.html\r\n[cpm]: https://github.org/kriszyp/cpm\r\n[volo]: http://volojs.org/\r\n[npm]: http://npmjs.org/\r\n[doh]: http://dojotoolkit.org/reference-guide/1.8/util/doh.html\r\n[download]: /kitsonk/hokan/archive/master.zip\r\n","google":"","note":"Don't delete this file! It's used internally to help with page regeneration."}